README.md
setup.cfg
setup.py
filemon/__init__.py
filemon/filemon.py
filemon.egg-info/PKG-INFO
filemon.egg-info/SOURCES.txt
filemon.egg-info/dependency_links.txt
filemon.egg-info/requires.txt
filemon.egg-info/top_level.txt