Metadata-Version: 2.1
Name: filemon
Version: 1.3
Summary: A file monitor tool compatible with Windows, Linux,  And MacOS.
Home-page: https://github.com/TheKingOfDuck/FileMonitor
Author: CoolCat
Author-email: root@thekingofduck.com
Requires-Dist: watchdog==6.0.0
Requires-Dist: filemon
Requires-Dist: argparse
